postgres_backup/__init__.py
postgres_backup/backup.py
postgres_backup/dummy.py
postgres_backup/logger.py
postgres_backup/exceptions/__init__.py
postgres_backup/exceptions/gcs.py
postgres_backup/schemas/__init__.py
postgres_backup/schemas/gcs.py
postgres_backup/schemas/providers.py
postgres_backup/upload/__init__.py
postgres_backup/upload/aws.py
postgres_backup/upload/gcs.py
postgres_backup/upload/providers.py
postgres_backup/utils/__init__.py
postgres_backup/utils/config.py
postgres_backup/utils/logger.py
postgres_backup-0.3.4.dist-info/LICENSE.txt
postgres_backup-0.3.4.dist-info/METADATA
postgres_backup-0.3.4.dist-info/WHEEL
postgres_backup-0.3.4.dist-info/top_level.txt
postgres_backup-0.3.4.dist-info/RECORD
