Metadata-Version: 2.1
Name: postgres-backup
Version: 0.3.4
Summary: Automation of the creation of backups of Postgres databases
Home-page: https://github.com/Nil-Andreu/postgres-backup
Author: Nil Andreu
Author-email: nilandreug@email.com
License: MIT
Keywords: backup,Postgres,SQL,database,PostgreSQL,Data Engineering
Classifier: Development Status :: 3 - Alpha
Classifier: Intended Audience :: Developers
Classifier: Topic :: Software Development :: Build Tools
Classifier: License :: OSI Approved :: MIT License
Classifier: Programming Language :: Python :: 3.8
Classifier: Programming Language :: Python :: 3.9
Classifier: Programming Language :: Python :: 3.10
License-File: LICENSE.txt
Requires-Dist: sh
Requires-Dist: pydantic (==1.10.4)
Provides-Extra: aws
Requires-Dist: boto3 ; extra == 'aws'
Provides-Extra: gcs
Requires-Dist: google (==3.0.0) ; extra == 'gcs'
Requires-Dist: google-cloud-storage (==2.7.0) ; extra == 'gcs'
